speechmatching/__init__.py
speechmatching/audio.py
speechmatching/config.py
speechmatching/match.py
speechmatching/model.py
speechmatching/recording.py
speechmatching/utils.py
speechmatching-1.0.0.dist-info/LICENSE.txt
speechmatching-1.0.0.dist-info/METADATA
speechmatching-1.0.0.dist-info/WHEEL
speechmatching-1.0.0.dist-info/top_level.txt
speechmatching-1.0.0.dist-info/RECORD
