Metadata-Version: 2.2
Name: speechmatching
Version: 1.0.0
Summary: Matching short audio segments of speech with each other.
Author-email: Auke Schuringa <auke.schuringa@proton.me>
License: MIT License
Project-URL: Homepage, https://github.com/W4RA/speechmatching
Project-URL: Issues, https://github.com/W4RA/speechmatching/issues
Project-URL: Repository, https://github.com/W4RA/speechmatching.git
Project-URL: Changelog, https://github.com/W4RA/speechmatching/blob/master/CHANGELOG.rst
Project-URL: Documentation, https://w4ra.github.io/speechmatching/
Classifier: Programming Language :: Python :: 3
Requires-Python: >=3.9
License-File: LICENSE.txt
Requires-Dist: ffmpeg-python
Requires-Dist: jellyfish
Requires-Dist: python-magic
Requires-Dist: numpy
Requires-Dist: docker
Provides-Extra: dev
Requires-Dist: pytype; extra == "dev"
Requires-Dist: types-requests; extra == "dev"
Requires-Dist: typing-extensions; extra == "dev"
Requires-Dist: sphinx; extra == "dev"
Requires-Dist: sphinxcontrib-applehelp; extra == "dev"
Requires-Dist: sphinxcontrib-devhelp; extra == "dev"
Requires-Dist: sphinxcontrib-htmlhelp; extra == "dev"
Requires-Dist: sphinxcontrib-jsmath; extra == "dev"
Requires-Dist: sphinxcontrib-qthelp; extra == "dev"
Requires-Dist: sphinxcontrib-serializinghtml; extra == "dev"
